PokerRL/__init__.py
PokerRL/_/CppWrapper.py
PokerRL/_/CrayonWrapper.py
PokerRL/_/__init__.py
PokerRL/cfr/CFRPlus.py
PokerRL/cfr/LinearCFR.py
PokerRL/cfr/VanillaCFR.py
PokerRL/cfr/_CFRBase.py
PokerRL/cfr/__init__.py
PokerRL/eval/__init__.py
PokerRL/eval/_/EvaluatorMasterBase.py
PokerRL/eval/_/__init__.py
PokerRL/eval/br/DistBRMaster.py
PokerRL/eval/br/LocalBRMaster.py
PokerRL/eval/br/__init__.py
PokerRL/eval/head_to_head/DistHead2HeadMaster.py
PokerRL/eval/head_to_head/H2HArgs.py
PokerRL/eval/head_to_head/LocalHead2HeadMaster.py
PokerRL/eval/head_to_head/__init__.py
PokerRL/eval/lbr/DistLBRMaster.py
PokerRL/eval/lbr/DistLBRWorker.py
PokerRL/eval/lbr/LBRArgs.py
PokerRL/eval/lbr/LocalLBRMaster.py
PokerRL/eval/lbr/LocalLBRWorker.py
PokerRL/eval/lbr/__init__.py
PokerRL/eval/lbr/_util.py
PokerRL/eval/rl_br/DistRLBRMaster.py
PokerRL/eval/rl_br/LocalRLBRMaster.py
PokerRL/eval/rl_br/RLBRArgs.py
PokerRL/eval/rl_br/__init__.py
PokerRL/eval/rl_br/_util.py
PokerRL/eval/rl_br/workers/__init__.py
PokerRL/eval/rl_br/workers/la/Dist_RLBR_LearnerActor.py
PokerRL/eval/rl_br/workers/la/Local_RLBR_LearnerActor.py
PokerRL/eval/rl_br/workers/la/__init__.py
PokerRL/eval/rl_br/workers/ps/Dist_RLBR_ParameterServer.py
PokerRL/eval/rl_br/workers/ps/Local_RLBR_ParameterServer.py
PokerRL/eval/rl_br/workers/ps/__init__.py
PokerRL/game/AgentTournament.py
PokerRL/game/InteractiveGame.py
PokerRL/game/Poker.py
PokerRL/game/PokerEnvStateDictEnums.py
PokerRL/game/PokerRange.py
PokerRL/game/__init__.py
PokerRL/game/bet_sets.py
PokerRL/game/games.py
PokerRL/game/poker_env_args.py
PokerRL/game/wrappers.py
PokerRL/game/_/EnvWrapperBuilderBase.py
PokerRL/game/_/__init__.py
PokerRL/game/_/look_up_table.py
PokerRL/game/_/cpp_wrappers/CppHandeval.py
PokerRL/game/_/cpp_wrappers/CppLUT.py
PokerRL/game/_/cpp_wrappers/__init__.py
PokerRL/game/_/cpp_wrappers/lib_hand_eval.dll
PokerRL/game/_/cpp_wrappers/lib_hand_eval.so
PokerRL/game/_/cpp_wrappers/lib_luts.dll
PokerRL/game/_/cpp_wrappers/lib_luts.so
PokerRL-0.0.3.dist-info/LICENSE
PokerRL-0.0.3.dist-info/METADATA
PokerRL-0.0.3.dist-info/WHEEL
PokerRL-0.0.3.dist-info/top_level.txt
PokerRL-0.0.3.dist-info/RECORD
