Metadata-Version: 2.1
Name: PokerRL
Version: 0.0.3
Summary: A framework for Reinforcement Learning in Poker.
Home-page: https://github.com/TinkeringCode/PokerRL
Author: Eric Steinberger
Author-email: ericsteinberger.est@gmail.com
License: MIT
Platform: UNKNOWN
Classifier: Programming Language :: Python :: 3
Classifier: Programming Language :: Python :: 3.6
Classifier: Programming Language :: Python :: 3.7
Classifier: License :: OSI Approved :: MIT License
Classifier: Intended Audience :: Developers
Classifier: Intended Audience :: Education
Classifier: Intended Audience :: Science/Research
Classifier: Operating System :: OS Independent
Requires-Dist: requests
Requires-Dist: gym (==0.10.9)
Requires-Dist: pycrayon (==0.5)
Requires-Dist: psutil
Provides-Extra: distributed
Requires-Dist: ray (==0.6.1); extra == 'distributed'
Requires-Dist: redis (==2.10.6); extra == 'distributed'
Requires-Dist: boto3; extra == 'distributed'
